{
  "metadata": {
    "experiment_id": "exp06_quant_catboost",
    "dataset_name": "static_20260127_092347",
    "timestamp": "2026-02-01T10:21:06.634811",
    "config_hash": "d39ce5"
  },
  "hyperparameters": {
    "depth": 4,
    "learning_rate": 0.0796300697310714,
    "iterations": 1000,
    "random_state": 42,
    "verbose": 500,
    "min_data_in_leaf": 15,
    "l2_leaf_reg": 0.4626308046856249,
    "loss_function": "RMSE",
    "eval_metric": "RMSE"
  },
  "results": {
    "rmse": 67.42289554769957,
    "mae": 54.34348347642396,
    "r2": 0.3274249585734701
  }
}