{
  "metadata": {
    "experiment_id": "exp02_catboost",
    "timestamp": "2025-10-19T10:29:58.587067",
    "config_hash": "d79597",
    "test_arch": "tesla"
  },
  "hyperparameters": {
    "depth": 2,
    "learning_rate": 0.08364387535595529,
    "iterations": 1000,
    "random_state": 42,
    "verbose": 500,
    "min_data_in_leaf": 58,
    "l2_leaf_reg": 0.2733640583979254,
    "loss_function": "RMSE",
    "eval_metric": "RMSE"
  },
  "results": {
    "rmse": 82.82190869217291,
    "mae": 70.9273907407245,
    "r2": -1.8715973835449136
  }
}